[
  {
    "type": "text",
    "text": "Standard SGT-100-2S Driver Package Acoustic Equipment Technical Requirement Specification",
    "page_idx": 0
  },
  {
    "type": "text",
    "text": "Specification Number: 64/03020193",
    "page_idx": 0
  },
  {
    "type": "text",
    "text": "Siemens Industrial Turbomachinery Department E O GT R&D",
    "page_idx": 0
  },
  {
    "type": "text",
    "text": "1 General Topics\n1.1 Introduction\nSiemens product development has developed a standardised package solution. The aims of this project are to:",
    "page_idx": 0
  },
  {
    "type": "text",
    "text": "• Create a product that is structured to fit varied markets through the use of pre engineered options\n• Reduce package purchase cost\n• Reduce the manufacturing time and costs\n• Reduce installation and maintenance time and cost",
    "page_idx": 0
  },
  {
    "type": "text",
    "text": "1.2 Description of the Main Scope of Supply\nThe acoustic package scope consists of",
    "page_idx": 1
  },
  {
    "type": "text",
    "text": "a) Acoustic enclosure and support steelwork where necessary.\nb) Ventilation system including fan(s), silencer, ventilation dampers, filter where required and duct work.",
    "page_idx": 1
  },
  {
    "type": "table",
    "table_caption": "General Split of supply",
    "table_body": [
      [
        "Configuration",
        "Sent to package build location",
        "Equipment sent from package build location to vendor",
        "Sent to site"
      ],
      [
        "Vertical roof mounted exhaust",
        "enclosure",
        "P2 cooler and oil mist eliminator Gas detectors",
        "Air handling equipment mounted on a frame Pipework Flame traps Oil cooler"
      ],
      [
        "Side exhaust, oil cooler on roof",
        "enclosure",
        "P2 cooler, oil mist eliminator Gas detectors",
        "Air handling equipment mounted on a frame Pipework Flame traps Oil cooler"
      ]
    ],
    "page_idx": 1
  },
  {
    "type": "text",
    "text": "2 References and Design Codes\na) The design shall comply with all applicable International and European Standards. The supplier shall define what standards are applicable.",
    "page_idx": 2
  },
  {
    "type": "text",
    "text": "3 General design requirements and design data\n3.1 Environmental design limits",
    "page_idx": 3
  },
  {
    "type": "table",
    "table_caption": "Environmental design limits",
    "table_body": [
      [
        "",
        "Onshore",
        "Coastal",
        "Offshore (Design TBA)"
      ],
      [
        "Standard temperature range(°C)",
        "-20 +43",
        "-20 +43",
        "-20 +43"
      ],
      [
        "High temperature option(°C)",
        "-15 +55",
        "-15 +55",
        "-15 +55"
      ],
      [
        "Low temperature option(°C)",
        "-50 +43",
        "-50 +43",
        "-50 +43"
      ],
      [
        "Operating effective wind speeds",
        "125mph (55m/s) (3s gusts)",
        "125mph (55m/s) (3s gusts)",
        "150mph (67m/s) (3s gusts)"
      ]
    ],
    "page_idx": 3
  },
  {
    "type": "text",
    "text": "3.3 Noise requirements\nNoise standard outdoor(85dB(A)) - Mean SPL measured at various points 1m from package plan view envelope",
    "page_idx": 5
  },
  {
    "type": "table",
    "table_caption": "Noise data - GT Turbine casing noise",
    "table_body": [
      [
        "Frequency (Hz)",
        "31",
        "63",
        "125",
        "250",
        "500",
        "1k",
        "2k",
        "2.5K",
        "3.15K",
        "4k",
        "5.0K",
        "6.3K",
        "8k"
      ],
      [
        "Noise Signature (dB, SPL)",
        "84",
        "85",
        "99",
        "100",
        "93",
        "95",
        "102",
        "-",
        "-",
        "116",
        "-",
        "-",
        "05"
      ]
    ],
    "page_idx": 7
  },
  {
    "type": "text",
    "text": "3.13 Engine mass flows and temperature\nThe gas turbine mass flow data quoted is subject to a +/- 3% tolerance.",
    "page_idx": 8
  }
]